plrs-0.1.5.dist-info/METADATA
plrs-0.1.5.dist-info/WHEEL
plrs/__init__.py
plrs/plrs.cpython-38-x86_64-linux-gnu.so
plrs-0.1.5.dist-info/RECORD
