Metadata-Version: 2.1
Name: plrs
Version: 0.1.5
Classifier: Intended Audience :: Developers
Classifier: License :: OSI Approved :: MIT License
Classifier: Operating System :: MacOS
Classifier: Operating System :: Microsoft :: Windows
Classifier: Operating System :: POSIX :: Linux
Classifier: Programming Language :: Python :: 3
Classifier: Programming Language :: Python :: 3.10
Classifier: Programming Language :: Python :: 3.6
Classifier: Programming Language :: Python :: 3.7
Classifier: Programming Language :: Python :: 3.8
Classifier: Programming Language :: Python :: 3.9
Classifier: Programming Language :: Python :: Implementation :: CPython
Classifier: Programming Language :: Python
Classifier: Programming Language :: Rust
Classifier: Typing :: Typed
Summary: The multi-tool of lexical analysis and tokenization.
Keywords: pyo3,lexer
Author: jakeroggenbuck <jakeroggenbuck2@gmail.com>
Author-email: jakeroggenbuck <jakeroggenbuck2@gmail.com>
License: MIT
Requires-Python: >=3.6
Project-URL: Source Code, https://github.com/JakeRoggenbuck/plrs
